{"info":{"year":2024,"version":"1.0","description":"VIA project exported to COCO format using VGG Image Annotator (http://www.robots.ox.ac.uk/~vgg/software/via/)","contributor":"","url":"http://www.robots.ox.ac.uk/~vgg/software/via/","date_created":"Tue Sep 24 2024 19:15:28 GMT-0400 (Eastern Daylight Time)"},"images":[{"id":1,"width":640,"height":480,"file_name":"lego-00.11.20-09.18.2024.jpg","license":0,"date_captured":""},{"id":2,"width":640,"height":480,"file_name":"lego-01.06.20-09.18.2024.jpg","license":0,"date_captured":""},{"id":3,"width":640,"height":480,"file_name":"lego-02.15.20-09.18.2024.jpg","license":0,"date_captured":""},{"id":4,"width":640,"height":480,"file_name":"lego-03.10.20-09.18.2024.jpg","license":0,"date_captured":""},{"id":5,"width":640,"height":480,"file_name":"lego-04.13.20-09.18.2024.jpg","license":0,"date_captured":""},{"id":6,"width":640,"height":480,"file_name":"lego-05.11.20-09.18.2024.jpg","license":0,"date_captured":""},{"id":7,"width":640,"height":480,"file_name":"lego-05.14.20-09.18.2024.jpg","license":0,"date_captured":""},{"id":8,"width":640,"height":480,"file_name":"lego-06.07.20-09.18.2024.jpg","license":0,"date_captured":""},{"id":9,"width":640,"height":480,"file_name":"lego-07.08.20-09.18.2024.jpg","license":0,"date_captured":""},{"id":10,"width":640,"height":480,"file_name":"lego-07.12.20-09.18.2024.jpg","license":0,"date_captured":""},{"id":11,"width":640,"height":480,"file_name":"lego-07.17.20-09.18.2024.jpg","license":0,"date_captured":""},{"id":12,"width":640,"height":480,"file_name":"lego-08.06.20-09.18.2024.jpg","license":0,"date_captured":""},{"id":13,"width":640,"height":480,"file_name":"lego-09.05.20-09.18.2024.jpg","license":0,"date_captured":""},{"id":14,"width":640,"height":480,"file_name":"lego-09.09.20-09.18.2024.jpg","license":0,"date_captured":""},{"id":15,"width":640,"height":480,"file_name":"lego-09.16.20-09.18.2024.jpg","license":0,"date_captured":""},{"id":16,"width":640,"height":480,"file_name":"lego-11.04.20-09.18.2024.jpg","license":0,"date_captured":""},{"id":17,"width":640,"height":480,"file_name":"lego-12.17.20-09.18.2024.jpg","license":0,"date_captured":""},{"id":18,"width":640,"height":480,"file_name":"lego-13.02.20-09.18.2024.jpg","license":0,"date_captured":""},{"id":19,"width":640,"height":480,"file_name":"lego-13.08.20-09.18.2024.jpg","license":0,"date_captured":""},{"id":20,"width":640,"height":480,"file_name":"lego-13.14.20-09.18.2024.jpg","license":0,"date_captured":""},{"id":21,"width":640,"height":480,"file_name":"lego-14.05.20-09.18.2024.jpg","license":0,"date_captured":""},{"id":22,"width":640,"height":480,"file_name":"lego-14.11.20-09.18.2024.jpg","license":0,"date_captured":""},{"id":23,"width":640,"height":480,"file_name":"lego-15.15.20-09.18.2024.jpg","license":0,"date_captured":""},{"id":24,"width":640,"height":480,"file_name":"lego-16.16.20-09.18.2024.jpg","license":0,"date_captured":""},{"id":25,"width":640,"height":480,"file_name":"lego-17.04.20-09.18.2024.jpg","license":0,"date_captured":""},{"id":26,"width":640,"height":480,"file_name":"lego-17.09.20-09.18.2024.jpg","license":0,"date_captured":""},{"id":27,"width":640,"height":480,"file_name":"lego-17.10.20-09.18.2024.jpg","license":0,"date_captured":""},{"id":28,"width":640,"height":480,"file_name":"lego-17.17.20-09.18.2024.jpg","license":0,"date_captured":""},{"id":29,"width":640,"height":480,"file_name":"lego-18.12.20-09.18.2024.jpg","license":0,"date_captured":""},{"id":30,"width":640,"height":480,"file_name":"lego-19.07.20-09.18.2024.jpg","license":0,"date_captured":""},{"id":31,"width":640,"height":480,"file_name":"lego-19.08.20-09.18.2024.jpg","license":0,"date_captured":""},{"id":32,"width":640,"height":480,"file_name":"lego-19.14.20-09.18.2024.jpg","license":0,"date_captured":""},{"id":33,"width":640,"height":480,"file_name":"lego-21.05.20-09.18.2024.jpg","license":0,"date_captured":""},{"id":34,"width":640,"height":480,"file_name":"lego-22.03.20-09.18.2024.jpg","license":0,"date_captured":""},{"id":35,"width":640,"height":480,"file_name":"lego-22.04.20-09.18.2024.jpg","license":0,"date_captured":""},{"id":36,"width":640,"height":480,"file_name":"lego-22.16.20-09.18.2024.jpg","license":0,"date_captured":""},{"id":37,"width":640,"height":480,"file_name":"lego-23.10.20-09.18.2024.jpg","license":0,"date_captured":""},{"id":38,"width":640,"height":480,"file_name":"lego-23.12.20-09.18.2024.jpg","license":0,"date_captured":""},{"id":39,"width":640,"height":480,"file_name":"lego-23.17.20-09.18.2024.jpg","license":0,"date_captured":""},{"id":40,"width":640,"height":480,"file_name":"lego-24.14.20-09.18.2024.jpg","license":0,"date_captured":""},{"id":41,"width":640,"height":480,"file_name":"lego-25.15.20-09.18.2024.jpg","license":0,"date_captured":""},{"id":42,"width":640,"height":480,"file_name":"lego-26.05.20-09.18.2024.jpg","license":0,"date_captured":""},{"id":43,"width":640,"height":480,"file_name":"lego-26.07.20-09.18.2024.jpg","license":0,"date_captured":""},{"id":44,"width":640,"height":480,"file_name":"lego-27.11.20-09.18.2024.jpg","license":0,"date_captured":""},{"id":45,"width":640,"height":480,"file_name":"lego-30.07.20-09.18.2024.jpg","license":0,"date_captured":""},{"id":46,"width":640,"height":480,"file_name":"lego-30.17.20-09.18.2024.jpg","license":0,"date_captured":""},{"id":47,"width":640,"height":480,"file_name":"lego-31.09.20-09.18.2024.jpg","license":0,"date_captured":""},{"id":48,"width":640,"height":480,"file_name":"lego-32.06.20-09.18.2024.jpg","license":0,"date_captured":""},{"id":49,"width":640,"height":480,"file_name":"lego-32.16.20-09.18.2024.jpg","license":0,"date_captured":""},{"id":50,"width":640,"height":480,"file_name":"lego-34.02.20-09.18.2024.jpg","license":0,"date_captured":""},{"id":51,"width":640,"height":480,"file_name":"lego-34.03.20-09.18.2024.jpg","license":0,"date_captured":""},{"id":52,"width":640,"height":480,"file_name":"lego-34.05.20-09.18.2024.jpg","license":0,"date_captured":""},{"id":53,"width":640,"height":480,"file_name":"lego-35.04.20-09.18.2024.jpg","license":0,"date_captured":""},{"id":54,"width":640,"height":480,"file_name":"lego-36.06.20-09.18.2024.jpg","license":0,"date_captured":""},{"id":55,"width":640,"height":480,"file_name":"lego-36.09.20-09.18.2024.jpg","license":0,"date_captured":""},{"id":56,"width":640,"height":480,"file_name":"lego-36.12.20-09.18.2024.jpg","license":0,"date_captured":""},{"id":57,"width":640,"height":480,"file_name":"lego-36.16.20-09.18.2024.jpg","license":0,"date_captured":""},{"id":58,"width":640,"height":480,"file_name":"lego-38.13.20-09.18.2024.jpg","license":0,"date_captured":""},{"id":59,"width":640,"height":480,"file_name":"lego-38.14.20-09.18.2024.jpg","license":0,"date_captured":""},{"id":60,"width":640,"height":480,"file_name":"lego-38.17.20-09.18.2024.jpg","license":0,"date_captured":""},{"id":61,"width":640,"height":480,"file_name":"lego-39.05.20-09.18.2024.jpg","license":0,"date_captured":""},{"id":62,"width":640,"height":480,"file_name":"lego-39.11.20-09.18.2024.jpg","license":0,"date_captured":""},{"id":63,"width":640,"height":480,"file_name":"lego-40.03.20-09.18.2024.jpg","license":0,"date_captured":""},{"id":64,"width":640,"height":480,"file_name":"lego-41.06.20-09.18.2024.jpg","license":0,"date_captured":""},{"id":65,"width":640,"height":480,"file_name":"lego-41.07.20-09.18.2024.jpg","license":0,"date_captured":""},{"id":66,"width":640,"height":480,"file_name":"lego-42.09.20-09.18.2024.jpg","license":0,"date_captured":""},{"id":67,"width":640,"height":480,"file_name":"lego-42.16.20-09.18.2024.jpg","license":0,"date_captured":""},{"id":68,"width":640,"height":480,"file_name":"lego-43.05.20-09.18.2024.jpg","license":0,"date_captured":""},{"id":69,"width":640,"height":480,"file_name":"lego-44.08.20-09.18.2024.jpg","license":0,"date_captured":""},{"id":70,"width":640,"height":480,"file_name":"lego-44.14.20-09.18.2024.jpg","license":0,"date_captured":""},{"id":71,"width":640,"height":480,"file_name":"lego-44.15.20-09.18.2024.jpg","license":0,"date_captured":""},{"id":72,"width":640,"height":480,"file_name":"lego-45.02.20-09.18.2024.jpg","license":0,"date_captured":""},{"id":73,"width":640,"height":480,"file_name":"lego-45.58.19-09.18.2024.jpg","license":0,"date_captured":""},{"id":74,"width":640,"height":480,"file_name":"lego-46.13.20-09.18.2024.jpg","license":0,"date_captured":""},{"id":75,"width":640,"height":480,"file_name":"lego-46.16.20-09.18.2024.jpg","license":0,"date_captured":""},{"id":76,"width":640,"height":480,"file_name":"lego-47.06.20-09.18.2024.jpg","license":0,"date_captured":""},{"id":77,"width":640,"height":480,"file_name":"lego-48.10.20-09.18.2024.jpg","license":0,"date_captured":""},{"id":78,"width":640,"height":480,"file_name":"lego-48.11.20-09.18.2024.jpg","license":0,"date_captured":""},{"id":79,"width":640,"height":480,"file_name":"lego-48.17.20-09.18.2024.jpg","license":0,"date_captured":""},{"id":80,"width":640,"height":480,"file_name":"lego-49.14.20-09.18.2024.jpg","license":0,"date_captured":""},{"id":81,"width":640,"height":480,"file_name":"lego-50.04.20-09.18.2024.jpg","license":0,"date_captured":""},{"id":82,"width":640,"height":480,"file_name":"lego-50.12.20-09.18.2024.jpg","license":0,"date_captured":""},{"id":83,"width":640,"height":480,"file_name":"lego-51.05.20-09.18.2024.jpg","license":0,"date_captured":""},{"id":84,"width":640,"height":480,"file_name":"lego-51.13.20-09.18.2024.jpg","license":0,"date_captured":""},{"id":85,"width":640,"height":480,"file_name":"lego-52.15.20-09.18.2024.jpg","license":0,"date_captured":""},{"id":86,"width":640,"height":480,"file_name":"lego-53.07.20-09.18.2024.jpg","license":0,"date_captured":""},{"id":87,"width":640,"height":480,"file_name":"lego-53.17.20-09.18.2024.jpg","license":0,"date_captured":""},{"id":88,"width":640,"height":480,"file_name":"lego-55.08.20-09.18.2024.jpg","license":0,"date_captured":""},{"id":89,"width":640,"height":480,"file_name":"lego-55.12.20-09.18.2024.jpg","license":0,"date_captured":""},{"id":90,"width":640,"height":480,"file_name":"lego-56.05.20-09.18.2024.jpg","license":0,"date_captured":""},{"id":91,"width":640,"height":480,"file_name":"lego-56.06.20-09.18.2024.jpg","license":0,"date_captured":""},{"id":92,"width":640,"height":480,"file_name":"lego-56.14.20-09.18.2024.jpg","license":0,"date_captured":""},{"id":93,"width":640,"height":480,"file_name":"lego-57.09.20-09.18.2024.jpg","license":0,"date_captured":""},{"id":94,"width":640,"height":480,"file_name":"lego-58.04.20-09.18.2024.jpg","license":0,"date_captured":""},{"id":95,"width":640,"height":480,"file_name":"lego-58.15.20-09.18.2024.jpg","license":0,"date_captured":""},{"id":96,"width":640,"height":480,"file_name":"lego-59.01.20-09.18.2024.jpg","license":0,"date_captured":""},{"id":97,"width":640,"height":480,"file_name":"lego-59.03.20-09.18.2024.jpg","license":0,"date_captured":""},{"id":98,"width":640,"height":480,"file_name":"lego-59.08.20-09.18.2024.jpg","license":0,"date_captured":""},{"id":99,"width":640,"height":480,"file_name":"lego-59.13.20-09.18.2024.jpg","license":0,"date_captured":""},{"id":100,"width":640,"height":480,"file_name":"lego-59.17.20-09.18.2024.jpg","license":0,"date_captured":""}],"annotations":[],"licenses":[{"id":0,"name":"Unknown License","url":""}],"categories":[]}